asyncio_pubsub/__init__.py
asyncio_pubsub/batch.py
asyncio_pubsub/client.py
asyncio_pubsub/example.py
asyncio_pubsub/example2.py
asyncio_pubsub-0.0.2.dist-info/METADATA
asyncio_pubsub-0.0.2.dist-info/RECORD
asyncio_pubsub-0.0.2.dist-info/WHEEL
asyncio_pubsub-0.0.2.dist-info/top_level.txt
